dau/__init__.py
dau/apps.py
dau/core.py
dau/tests.py
dau-0.1.3.dist-info/WHEEL
dau-0.1.3.dist-info/METADATA
dau-0.1.3.dist-info/RECORD
