Metadata-Version: 2.1
Name: dau
Version: 0.1.3
Summary: Automatic user creation at Django startup.
Home-page: https://github.com/AndreGuerra123/dau
License: MIT
Author: AndreGuerra123
Author-email: guerraandre@hotmail.com
Requires-Python: >=3.6,<4.0
Classifier: License :: OSI Approved :: MIT License
Classifier: Programming Language :: Python :: 3
Classifier: Programming Language :: Python :: 3.6
Classifier: Programming Language :: Python :: 3.7
Requires-Dist: django (>=2.1,<3.0)
Project-URL: Repository, https://github.com/AndreGuerra123/dau
